arclet/entari/__init__.py
arclet/entari/builtins/auto_reload.py
arclet/entari/builtins/echo.py
arclet/entari/builtins/help.py
arclet/entari/builtins/inspect/README.md
arclet/entari/builtins/inspect/__init__.py
arclet/entari/builtins/inspect/i18n/.config.json
arclet/entari/builtins/inspect/i18n/.lang.schema.json
arclet/entari/builtins/inspect/i18n/.template.json
arclet/entari/builtins/inspect/i18n/.template.schema.json
arclet/entari/builtins/inspect/i18n/__init__.py
arclet/entari/builtins/inspect/i18n/de-DE.json
arclet/entari/builtins/inspect/i18n/en-UK.json
arclet/entari/builtins/inspect/i18n/en-US.json
arclet/entari/builtins/inspect/i18n/fr-FR.json
arclet/entari/builtins/inspect/i18n/ja-JP.json
arclet/entari/builtins/inspect/i18n/model.py
arclet/entari/builtins/inspect/i18n/ru-RU.json
arclet/entari/builtins/inspect/i18n/zh-CN.json
arclet/entari/builtins/inspect/i18n/zh-TW.json
arclet/entari/builtins/lang.py
arclet/entari/command/__init__.py
arclet/entari/command/argv.py
arclet/entari/command/model.py
arclet/entari/command/plugin.py
arclet/entari/command/provider.py
arclet/entari/config/__init__.py
arclet/entari/config/dc_schema.py
arclet/entari/config/file.py
arclet/entari/config/format/toml.py
arclet/entari/config/model.py
arclet/entari/config/models/default.py
arclet/entari/config/models/msgspec_.py
arclet/entari/config/models/pyd.py
arclet/entari/config/util.py
arclet/entari/core.py
arclet/entari/event/__init__.py
arclet/entari/event/base.py
arclet/entari/event/command.py
arclet/entari/event/config.py
arclet/entari/event/lifespan.py
arclet/entari/event/plugin.py
arclet/entari/event/send.py
arclet/entari/exceptions.py
arclet/entari/filter/__init__.py
arclet/entari/filter/common.py
arclet/entari/filter/message.py
arclet/entari/localdata.py
arclet/entari/logger.py
arclet/entari/message.py
arclet/entari/plugin/__init__.py
arclet/entari/plugin/model.py
arclet/entari/plugin/model.pyi
arclet/entari/plugin/module.py
arclet/entari/plugin/service.py
arclet_entari-0.16.8.dist-info/METADATA
arclet_entari-0.16.8.dist-info/WHEEL
arclet_entari-0.16.8.dist-info/entry_points.txt
arclet_entari-0.16.8.dist-info/licenses/LICENSE
arclet_entari-0.16.8.dist-info/RECORD
