Metadata-Version: 2.1
Name: arclet-entari
Version: 0.16.8
Summary: Simple IM Framework based on satori-python
Author-Email: RF-Tar-Railt <rf_tar_railt@qq.com>
License: MIT
Classifier: Programming Language :: Python :: 3.10
Classifier: Programming Language :: Python :: 3.11
Classifier: Programming Language :: Python :: 3.12
Classifier: Programming Language :: Python :: 3.13
Classifier: Programming Language :: Python :: 3.14
Classifier: License :: OSI Approved :: MIT License
Classifier: Intended Audience :: Developers
Classifier: Topic :: Software Development :: Libraries
Classifier: Topic :: Communications :: Chat
Classifier: Topic :: Internet
Classifier: Topic :: Software Development :: Libraries :: Application Frameworks
Classifier: Framework :: AsyncIO
Classifier: Operating System :: OS Independent
Project-URL: homepage, https://arclet.top
Project-URL: repository, https://github.com/ArcletProject/Entari
Requires-Python: >=3.10
Requires-Dist: arclet-letoderea<0.20.0,>=0.19.6
Requires-Dist: arclet-alconna<2.0.0,>=1.8.42
Requires-Dist: satori-python-core>=0.17.3
Requires-Dist: satori-python-client>=0.17.3
Requires-Dist: arclet-alconna-tools>=0.7.3
Requires-Dist: nonestorage>=0.1.0
Provides-Extra: yaml
Requires-Dist: ruamel-yaml>=0.18.10; extra == "yaml"
Provides-Extra: cron
Requires-Dist: croniter>=5.0.1; extra == "cron"
Provides-Extra: reload
Requires-Dist: watchfiles>=1.0.3; extra == "reload"
Provides-Extra: dotenv
Requires-Dist: python-dotenv>=1.0.1; extra == "dotenv"
Provides-Extra: full
Requires-Dist: croniter>=5.0.1; extra == "full"
Requires-Dist: watchfiles>=1.0.3; extra == "full"
Requires-Dist: python-dotenv>=1.0.1; extra == "full"
Requires-Dist: ruamel-yaml>=0.18.10; extra == "full"
Requires-Dist: entari-cli>=0.1.0; extra == "full"
Provides-Extra: pydantic
Requires-Dist: pydantic>=2.10.6; extra == "pydantic"
Provides-Extra: msgspec
Requires-Dist: msgspec>=0.19.0; extra == "msgspec"
Provides-Extra: toml
Requires-Dist: tomlkit>=0.13.3; extra == "toml"
Provides-Extra: cli
Requires-Dist: entari-cli>=0.1.0; extra == "cli"
Provides-Extra: rich
Requires-Dist: rich>=14.1.0; extra == "rich"
